[{"name":"awesome-osx-command-line","url":"https://github.com/herrbischoff/awesome-osx-command-line","description":"Use your OS X terminal shell to do awesome things."},{"name":"design-patterns-for-humans","url":"https://github.com/kamranahmedse/design-patterns-for-humans","description":"Design Patterns for Humans™ - An ultra-simplified explanation"},{"name":"freeCodeCamp","url":"https://github.com/freeCodeCamp/freeCodeCamp","description":"The https://freeCodeCamp.com open source codebase and curriculum. Learn to code and help nonprofits."},{"name":"awless","url":"https://github.com/wallix/awless","description":"A Mighty CLI for AWS"},{"name":"awesome-deep-learning-papers","url":"https://github.com/terryum/awesome-deep-learning-papers","description":"The most cited deep learning papers"},{"name":"trevor","url":"https://github.com/vadimdemedes/trevor","description":" Your own Travis CI to run tests locally"},{"name":"os01","url":"https://github.com/tuhdo/os01","description":"Bootstrap yourself to write an OS from scratch. A book for self-learner."},{"name":"Alerter","url":"https://github.com/Tapadoo/Alerter","description":"An Android Alerting Library"},{"name":"tensorflow","url":"https://github.com/tensorflow/tensorflow","description":"Computation using data flow graphs for scalable machine learning"},{"name":"AirSim","url":"https://github.com/Microsoft/AirSim","description":"Open source simulator based on Unreal Engine for autonomous vehicles from Microsoft AI & Research"},{"name":"ipyvolume","url":"https://github.com/maartenbreddels/ipyvolume","description":"IPython widget for rendering 3d volumes and glyphs in the Jupter notebook"},{"name":"interview-questions-in-javascript","url":"https://github.com/kennymkchan/interview-questions-in-javascript","description":"A mostly reasonable collection of technical software development interview questions solved in Javascript"},{"name":"botpress","url":"https://github.com/botpress/botpress","description":" The only sane way of building great bots. "},{"name":"cpython","url":"https://github.com/python/cpython","description":"The Python programming language"},{"name":"awesome-creative-coding","url":"https://github.com/terkelg/awesome-creative-coding","description":" Creative Coding, Generative Art, Interaction Design, Resources."},{"name":"AnimatedCollectionViewLayout","url":"https://github.com/KelvinJin/AnimatedCollectionViewLayout","description":"A UICollectionViewLayout subclass that adds custom transitions/animations to the UICollectionView without effecting your existing code."},{"name":"awesome","url":"https://github.com/sindresorhus/awesome","description":" Curated list of awesome lists"},{"name":"mmake","url":"https://github.com/tj/mmake","description":"Modern Make"},{"name":"be-a-professional-programmer","url":"https://github.com/stanzhai/be-a-professional-programmer","description":"成为专业程序员路上用到的各种优秀资料、神器及框架"},{"name":"CreepyCodeCollection","url":"https://github.com/MinhasKamal/CreepyCodeCollection","description":"A Nonsense Collection of Disgusting Codes (code-golf-golfing-quine-obfuscated-signature-polyglot-amazing-interesting-strange-weird-mysterious-absurd-spooky-program-funny-fun-language)"},{"name":"NeteaseCloudWebApp","url":"https://github.com/javaSwing/NeteaseCloudWebApp","description":"This is a vue for NeteaseCloud projects!"},{"name":"open-source-guide","url":"https://github.com/github/open-source-guide","description":"Community guides for open source creators"},{"name":"beehive","url":"https://github.com/muesli/beehive","description":"A flexible event and agent system with lots of bees"},{"name":"filmic-blender","url":"https://github.com/sobotka/filmic-blender","description":"Filmic View and Look Transformations for Blender"},{"name":"data-selfie","url":"https://github.com/d4t4x/data-selfie","description":"Description Not Provided"}]
